{
    "26-Jan-2021": "Republic Day",
    "11-Mar-2021": "Mahashivratri",
    "29-Mar-2021": "Holi",
    "02-Apr-2021": "Good Friday",
    "14-Apr-2021": "Dr.Baba Saheb Ambedkar Jayanti",
    "21-Apr-2021": "Ram Navami",
    "25-Apr-2021": "Mahavir Jayanti",
    "01-May-2021": "Maharashtra Day",
    "13-May-2021": "Id-Ul-Fitr (Ramzan ID)",
    "21-Jul-2021": "Bakri Id",
    "15-Aug-2021": "Independence Day",
    "19-Aug-2021": "Moharram",
    "10-Sep-2021": "Ganesh Chaturthi",
    "02-Oct-2021": "Mahatma Gandhi Jayanti",
    "15-Oct-2021": "Dussehra",
    "05-Nov-2021": "Diwali-Balipratipada",
    "19-Nov-2021": "Gurunanak Jayanti",
    "25-Dec-2021": "Christmas"
}